valor/__init__.py
valor/client.py
valor/coretypes.py
valor/enums.py
valor/exceptions.py
valor/metatypes.py
valor/type_checks.py
valor/viz.py
valor/schemas/__init__.py
valor/schemas/evaluation.py
valor/schemas/filters.py
valor/schemas/symbolic/__init__.py
valor/schemas/symbolic/collections.py
valor/schemas/symbolic/operators.py
valor/schemas/symbolic/types.py
valor_client-0.33.19.dist-info/LICENSE
valor_client-0.33.19.dist-info/METADATA
valor_client-0.33.19.dist-info/WHEEL
valor_client-0.33.19.dist-info/top_level.txt
valor_client-0.33.19.dist-info/RECORD
