Metadata-Version: 2.1
Name: valor-client
Version: 0.33.19
Summary: Python client for the Valor evaluation store
License: MIT License
Project-URL: homepage, https://www.striveworks.com
Requires-Python: >=3.10
License-File: LICENSE
Requires-Dist: requests
Requires-Dist: Pillow>=9.1.0
Requires-Dist: numpy
Requires-Dist: importlib_metadata; python_version < "3.8"
Requires-Dist: tqdm
Requires-Dist: packaging
Provides-Extra: test
Requires-Dist: pytest; extra == "test"
Requires-Dist: coverage; extra == "test"
